itaxotools/__pyinstaller/hook-itaxotools.haplodemo.py
itaxotools/haplodemo/__init__.py
itaxotools/haplodemo/__main__.py
itaxotools/haplodemo/_version.py
itaxotools/haplodemo/demos.py
itaxotools/haplodemo/dialogs.py
itaxotools/haplodemo/history.py
itaxotools/haplodemo/layout.py
itaxotools/haplodemo/models.py
itaxotools/haplodemo/palettes.py
itaxotools/haplodemo/scene.py
itaxotools/haplodemo/settings.py
itaxotools/haplodemo/types.py
itaxotools/haplodemo/utility.py
itaxotools/haplodemo/views.py
itaxotools/haplodemo/visualizer.py
itaxotools/haplodemo/widgets.py
itaxotools/haplodemo/window.py
itaxotools/haplodemo/zoom.py
itaxotools/haplodemo/items/__init__.py
itaxotools/haplodemo/items/bezier.py
itaxotools/haplodemo/items/boundary.py
itaxotools/haplodemo/items/boxes.py
itaxotools/haplodemo/items/edges.py
itaxotools/haplodemo/items/labels.py
itaxotools/haplodemo/items/legend.py
itaxotools/haplodemo/items/nodes.py
itaxotools/haplodemo/items/protocols.py
itaxotools/haplodemo/items/rotate.py
itaxotools/haplodemo/items/scale.py
itaxotools/haplodemo/items/types.py
itaxotools_haplodemo-0.3.0.dist-info/licenses/LICENSE.txt
itaxotools_haplodemo-0.3.0.dist-info/METADATA
itaxotools_haplodemo-0.3.0.dist-info/WHEEL
itaxotools_haplodemo-0.3.0.dist-info/entry_points.txt
itaxotools_haplodemo-0.3.0.dist-info/top_level.txt
itaxotools_haplodemo-0.3.0.dist-info/RECORD
